ue_asset_cli/__init__.py
ue_asset_cli/_version.py
ue_asset_cli/cli.py
ue_asset_cli/downloader.py
ue_asset_cli/egs_types.py
ue_asset_cli/library.py
ue_asset_cli/login.py
ue_asset_cli/main.py
ue_asset_cli-0.1.1.dist-info/METADATA
ue_asset_cli-0.1.1.dist-info/WHEEL
ue_asset_cli-0.1.1.dist-info/entry_points.txt
ue_asset_cli-0.1.1.dist-info/RECORD
