Metadata-Version: 2.1
Name: ue-asset-cli
Version: 0.1.1
Summary: A linux-compatible command-line interface to download Assets from the Epic Game Store Marketplace.
Project-URL: Repository, https://github.com/jwindgassen/ue-asset-cli
Project-URL: Issues, https://github.com/jwindgassen/ue-asset-cli/issues
Author-email: Jonathan Windgassen <j.windgassen@fz-juelich.de>
License-Expression: MIT
Keywords: EGS,EOS,Epic Games,Marketplace,UE,UE4,UE5,Unreal Engine
Classifier: Development Status :: 3 - Alpha
Classifier: Environment :: Console
Classifier: Intended Audience :: Developers
Classifier: License :: OSI Approved :: MIT License
Classifier: Natural Language :: English
Classifier: Operating System :: OS Independent
Classifier: Programming Language :: Python
Classifier: Programming Language :: Python :: 3.9
Classifier: Programming Language :: Python :: 3.10
Classifier: Programming Language :: Python :: 3.11
Classifier: Programming Language :: Python :: 3.12
Classifier: Topic :: Games/Entertainment
Classifier: Topic :: Software Development
Classifier: Topic :: Software Development :: Libraries
Classifier: Topic :: Utilities
Requires-Python: >=3.9
Requires-Dist: keyring
Requires-Dist: requests
Requires-Dist: tqdm
